{
  "runDate": "2026-04-22",
  "runAt": "2026-04-22T09:11:00.931Z",
  "totalLoads": 22494,
  "previousTotal": 22015,
  "netChange": 479,
  "added": 17380,
  "removed": 16901,
  "avgPay": 1144,
  "loadsWithPay": 15712,
  "equipmentTypes": [
    [
      "Flatbed",
      11750
    ],
    [
      "Step Deck",
      5255
    ],
    [
      "Dry Van",
      3455
    ],
    [
      "Refrigerated",
      1210
    ],
    [
      "Power Only",
      400
    ],
    [
      "Hotshot",
      75
    ],
    [
      "48 FT",
      62
    ],
    [
      "TARPS",
      61
    ],
    [
      "Box Truck",
      41
    ],
    [
      "Other",
      37
    ],
    [
      "Lowboy",
      31
    ],
    [
      "Curtain Van",
      25
    ],
    [
      "PARTIAL",
      20
    ],
    [
      "53 FT",
      16
    ],
    [
      "Container",
      15
    ],
    [
      "FLATBED / DRY VAN",
      5
    ],
    [
      "26 FT",
      4
    ],
    [
      "Dump Trailer",
      3
    ],
    [
      "CURTAIN_SIDE",
      2
    ],
    [
      "24 FT",
      2
    ],
    [
      "20 FT",
      2
    ],
    [
      "LIFT-GATE",
      2
    ],
    [
      "Cargo Van",
      1
    ],
    [
      "HOTSHOT",
      1
    ],
    [
      "32 FT",
      1
    ],
    [
      "S",
      1
    ],
    [
      "REEFER",
      1
    ],
    [
      "HTRM",
      1
    ],
    [
      "STEPDECK",
      1
    ],
    [
      "OVERDIMENSIONAL",
      1
    ],
    [
      "30 FT",
      1
    ],
    [
      "LB13",
      1
    ],
    [
      "53SD",
      1
    ],
    [
      "Hopper Bottom",
      1
    ],
    [
      "FLAT OR DROP",
      1
    ],
    [
      "O",
      1
    ],
    [
      "Tanker",
      1
    ],
    [
      "LOW9",
      1
    ],
    [
      "LP9E",
      1
    ],
    [
      "LO8E",
      1
    ],
    [
      "REF2",
      1
    ],
    [
      "REFR",
      1
    ],
    [
      "REF1",
      1
    ]
  ],
  "topPickupStates": [
    [
      "GA",
      2438
    ],
    [
      "AL",
      2418
    ],
    [
      "NC",
      1226
    ],
    [
      "IL",
      1184
    ],
    [
      "CA",
      1070
    ],
    [
      "MS",
      1061
    ],
    [
      "MI",
      983
    ],
    [
      "AR",
      929
    ],
    [
      "SC",
      917
    ],
    [
      "MA",
      829
    ],
    [
      "IN",
      816
    ],
    [
      "VA",
      661
    ],
    [
      "WI",
      621
    ],
    [
      "KY",
      614
    ],
    [
      "NJ",
      578
    ],
    [
      "TN",
      539
    ],
    [
      "NY",
      533
    ],
    [
      "MD",
      529
    ],
    [
      "LA",
      483
    ],
    [
      "MN",
      462
    ]
  ]
}