{
  "runDate": "2026-04-24",
  "runAt": "2026-04-24T09:10:55.389Z",
  "totalLoads": 26776,
  "previousTotal": 35362,
  "netChange": -8586,
  "added": 6617,
  "removed": 15203,
  "avgPay": 1132,
  "loadsWithPay": 18743,
  "equipmentTypes": [
    [
      "Flatbed",
      13236
    ],
    [
      "Step Deck",
      5937
    ],
    [
      "Dry Van",
      4913
    ],
    [
      "Refrigerated",
      1905
    ],
    [
      "Power Only",
      500
    ],
    [
      "Hotshot",
      106
    ],
    [
      "Lowboy",
      44
    ],
    [
      "Box Truck",
      44
    ],
    [
      "Curtain Van",
      24
    ],
    [
      "Other",
      21
    ],
    [
      "Container",
      13
    ],
    [
      "Cargo Van",
      4
    ],
    [
      "Dump Trailer",
      4
    ],
    [
      "48 FT",
      2
    ],
    [
      "TARPS",
      2
    ],
    [
      "26 FT",
      2
    ],
    [
      "PARTIAL",
      2
    ],
    [
      "53 FT",
      2
    ],
    [
      "Tanker",
      1
    ],
    [
      "LIFT-GATE",
      1
    ],
    [
      "REEFER",
      1
    ],
    [
      "28 FT",
      1
    ],
    [
      "CURTAIN_SIDE",
      1
    ],
    [
      "Hopper Bottom",
      1
    ],
    [
      "FLAT OR DROP",
      1
    ],
    [
      "LB13",
      1
    ],
    [
      "53SD",
      1
    ],
    [
      "24 FT",
      1
    ],
    [
      "STEPDECK",
      1
    ],
    [
      "O",
      1
    ],
    [
      "LOW9",
      1
    ],
    [
      "LP9E",
      1
    ],
    [
      "LO8E",
      1
    ]
  ],
  "topPickupStates": [
    [
      "TX",
      2701
    ],
    [
      "GA",
      1930
    ],
    [
      "AL",
      1787
    ],
    [
      "FL",
      1613
    ],
    [
      "OH",
      1294
    ],
    [
      "NC",
      1180
    ],
    [
      "CA",
      1011
    ],
    [
      "SC",
      1006
    ],
    [
      "MA",
      998
    ],
    [
      "IL",
      993
    ],
    [
      "PA",
      928
    ],
    [
      "IN",
      847
    ],
    [
      "MI",
      770
    ],
    [
      "AR",
      749
    ],
    [
      "VA",
      749
    ],
    [
      "MS",
      719
    ],
    [
      "NY",
      590
    ],
    [
      "MN",
      548
    ],
    [
      "NJ",
      530
    ],
    [
      "TN",
      482
    ]
  ]
}