{
  "runDate": "2026-04-15",
  "runAt": "2026-04-15T08:59:04.621Z",
  "totalLoads": 22900,
  "previousTotal": 24932,
  "netChange": -2032,
  "added": 21188,
  "removed": 23220,
  "avgPay": 1164,
  "loadsWithPay": 16085,
  "equipmentTypes": [
    [
      "Flatbed",
      11446
    ],
    [
      "Step Deck",
      5336
    ],
    [
      "Dry Van",
      3830
    ],
    [
      "Refrigerated",
      1404
    ],
    [
      "Power Only",
      394
    ],
    [
      "Other",
      128
    ],
    [
      "Hotshot",
      82
    ],
    [
      "Box Truck",
      45
    ],
    [
      "48 FT",
      39
    ],
    [
      "TARPS",
      39
    ],
    [
      "Lowboy",
      34
    ],
    [
      "Curtain Van",
      27
    ],
    [
      "53 FT",
      17
    ],
    [
      "PARTIAL",
      15
    ],
    [
      "Container",
      14
    ],
    [
      "O",
      5
    ],
    [
      "Tanker",
      4
    ],
    [
      "Cargo Van",
      4
    ],
    [
      "Dump Trailer",
      4
    ],
    [
      "Hopper Bottom",
      3
    ],
    [
      "FLAT OR DROP",
      3
    ],
    [
      "26 FT",
      3
    ],
    [
      "CURTAIN_SIDE",
      2
    ],
    [
      "30 FT",
      2
    ],
    [
      "HTRM",
      1
    ],
    [
      "S",
      1
    ],
    [
      "FCON",
      1
    ],
    [
      "PFL",
      1
    ],
    [
      "HOTSHOT",
      1
    ],
    [
      "32 FT",
      1
    ],
    [
      "SDCT",
      1
    ],
    [
      "STEP",
      1
    ],
    [
      "FLAT",
      1
    ],
    [
      "STEPDECK",
      1
    ],
    [
      "40 FT",
      1
    ],
    [
      "OVERDIMENSIONAL",
      1
    ],
    [
      "20 FT",
      1
    ],
    [
      "REF2",
      1
    ],
    [
      "REFR",
      1
    ],
    [
      "REF1",
      1
    ],
    [
      "LO4E",
      1
    ],
    [
      "LO5E",
      1
    ],
    [
      "DOLY",
      1
    ],
    [
      "HOTS",
      1
    ]
  ],
  "topPickupStates": [
    [
      "GA",
      2568
    ],
    [
      "AL",
      2294
    ],
    [
      "SC",
      1222
    ],
    [
      "CA",
      1182
    ],
    [
      "AR",
      1176
    ],
    [
      "IL",
      1127
    ],
    [
      "NC",
      1114
    ],
    [
      "MS",
      1071
    ],
    [
      "MI",
      926
    ],
    [
      "VA",
      848
    ],
    [
      "IN",
      764
    ],
    [
      "MA",
      734
    ],
    [
      "LA",
      618
    ],
    [
      "NY",
      556
    ],
    [
      "WI",
      550
    ],
    [
      "NJ",
      541
    ],
    [
      "KY",
      512
    ],
    [
      "OK",
      482
    ],
    [
      "TN",
      469
    ],
    [
      "MN",
      444
    ]
  ]
}